discord_winhook/__init__.py
discord_winhook/base.py
discord_winhook/info.py
discord_winhook/screenshot.py
discord_winhook/subprocess.py
discord_winhook-0.1.2.dist-info/METADATA
discord_winhook-0.1.2.dist-info/WHEEL
discord_winhook-0.1.2.dist-info/licenses/LICENSE
discord_winhook-0.1.2.dist-info/RECORD
